contextplus/__init__.py
contextplus/main.py
contextplus/model.py
contextplus/wiki.py
contextplus-0.1.4.dist-info/LICENSE
contextplus-0.1.4.dist-info/METADATA
contextplus-0.1.4.dist-info/WHEEL
contextplus-0.1.4.dist-info/RECORD
