Metadata-Version: 2.1
Name: contextplus
Version: 0.1.4
Summary: Empowering Conversations with Real-Time Facts
Author: Florian Wunderlich
Requires-Python: >=3.9,<4.0
Classifier: Programming Language :: Python :: 3
Classifier: Programming Language :: Python :: 3.9
Classifier: Programming Language :: Python :: 3.10
Classifier: Programming Language :: Python :: 3.11
Classifier: Programming Language :: Python :: 3.12
Requires-Dist: sentence-transformers (>=2.7.0,<3.0.0)
Requires-Dist: transformers (>=4.40.2,<5.0.0)
Requires-Dist: wikipedia (>=1.4.0,<2.0.0)
